qb/__main__.py
qb/compiler_functions/__init__.py
qb/compiler_functions/cleaner.py
qb/compiler_functions/keyword_replacement.py
qb/compiler_functions/multi_line_lambda.py
qb/compiler_functions/pipe_operator.py
qb/compiler_functions/string_cryptography.py
qb/qbstd/__init__.py
qb/qbstd/functions.py
qb/qbstd/types.py
qb/qbstd/wrappers.py
lsqbc-0.1.1.dist-info/entry_points.txt
lsqbc-0.1.1.dist-info/METADATA
lsqbc-0.1.1.dist-info/WHEEL
lsqbc-0.1.1.dist-info/RECORD
